{
	"info": {
		"_postman_id": "ea04d9b8-0386-4fc8-83c3-f0e3e6a4bec1",
		"name": "Labefy",
		"schema": "https://schema.getpostman.com/json/collection/v2.1.0/collection.json",
		"_exporter_id": "21554552"
	},
	"item": [
		{
			"name": "createPlaylist",
			"request": {
				"method": "POST",
				"header": [
					{
						"key": "Authorization",
						"value": "guilherme-beutler-freire",
						"type": "text"
					}
				],
				"body": {
					"mode": "raw",
					"raw": "{\r\n    \"name\": \"playlist-indie\" \r\n}"
				},
				"url": {
					"raw": "https://us-central1-labenu-apis.cloudfunctions.net/labefy/playlists",
					"protocol": "https",
					"host": [
						"us-central1-labenu-apis",
						"cloudfunctions",
						"net"
					],
					"path": [
						"labefy",
						"playlists"
					]
				}
			},
			"response": []
		},
		{
			"name": "getAllPlaylists",
			"request": {
				"method": "GET",
				"header": [
					{
						"key": "Authorization",
						"value": "guilherme-beutler-freire",
						"type": "text"
					}
				],
				"url": {
					"raw": "https://us-central1-labenu-apis.cloudfunctions.net/labefy/playlists",
					"protocol": "https",
					"host": [
						"us-central1-labenu-apis",
						"cloudfunctions",
						"net"
					],
					"path": [
						"labefy",
						"playlists"
					]
				}
			},
			"response": []
		},
		{
			"name": "addTrackToPlaylist",
			"request": {
				"method": "POST",
				"header": [
					{
						"key": "Authorization",
						"value": "guilherme-beutler-freire",
						"type": "text"
					}
				],
				"body": {
					"mode": "raw",
					"raw": "{\r\n    \"name\": \"Getaway Car\", \r\n    \"artist\": \"Audioslave\",\r\n    \"url\": \"https://www.youtube.com/watch?v=8h1v47JDcqg\"\r\n}",
					"options": {
						"raw": {
							"language": "json"
						}
					}
				},
				"url": {
					"raw": "https://us-central1-labenu-apis.cloudfunctions.net/labefy/playlists/:playlistId/tracks",
					"protocol": "https",
					"host": [
						"us-central1-labenu-apis",
						"cloudfunctions",
						"net"
					],
					"path": [
						"labefy",
						"playlists",
						":playlistId",
						"tracks"
					],
					"variable": [
						{
							"key": "playlistId",
							"value": "bba04a49-25d3-48d9-8b10-4e104a86e477"
						}
					]
				}
			},
			"response": []
		},
		{
			"name": "getPlaylistTracks",
			"request": {
				"method": "GET",
				"header": [
					{
						"key": "Authorization",
						"value": "guilherme-beutler-freire",
						"type": "text"
					}
				],
				"url": {
					"raw": "https://us-central1-labenu-apis.cloudfunctions.net/labefy/playlists/:playlistId/tracks",
					"protocol": "https",
					"host": [
						"us-central1-labenu-apis",
						"cloudfunctions",
						"net"
					],
					"path": [
						"labefy",
						"playlists",
						":playlistId",
						"tracks"
					],
					"variable": [
						{
							"key": "playlistId",
							"value": "d7d9848a-8ffd-4572-a71d-52fe2ceff1f5"
						}
					]
				}
			},
			"response": []
		},
		{
			"name": "searchPlaylist",
			"request": {
				"method": "GET",
				"header": [
					{
						"key": "Authorization",
						"value": "guilherme-beutler-freire",
						"type": "text"
					}
				],
				"url": {
					"raw": "https://us-central1-labenu-apis.cloudfunctions.net/labefy/playlists/search?name=indie",
					"protocol": "https",
					"host": [
						"us-central1-labenu-apis",
						"cloudfunctions",
						"net"
					],
					"path": [
						"labefy",
						"playlists",
						"search"
					],
					"query": [
						{
							"key": "name",
							"value": "indie"
						}
					]
				}
			},
			"response": []
		},
		{
			"name": "deletePlaylist",
			"request": {
				"method": "DELETE",
				"header": [],
				"url": {
					"raw": "https://us-central1-labenu-apis.cloudfunctions.net/labefy/playlists/:playlistId",
					"protocol": "https",
					"host": [
						"us-central1-labenu-apis",
						"cloudfunctions",
						"net"
					],
					"path": [
						"labefy",
						"playlists",
						":playlistId"
					],
					"variable": [
						{
							"key": "playlistId",
							"value": "bba04a49-25d3-48d9-8b10-4e104a86e477"
						}
					]
				}
			},
			"response": []
		},
		{
			"name": "removeTrackFromPlaylist",
			"request": {
				"method": "DELETE",
				"header": [],
				"url": {
					"raw": "https://us-central1-labenu-apis.cloudfunctions.net/labefy/playlists/:playlistId/tracks/:trackId",
					"protocol": "https",
					"host": [
						"us-central1-labenu-apis",
						"cloudfunctions",
						"net"
					],
					"path": [
						"labefy",
						"playlists",
						":playlistId",
						"tracks",
						":trackId"
					],
					"variable": [
						{
							"key": "playlistId",
							"value": "bba04a49-25d3-48d9-8b10-4e104a86e477"
						},
						{
							"key": "trackId",
							"value": "7778f460-5a05-4511-93fc-afe934152989"
						}
					]
				}
			},
			"response": []
		}
	],
	"event": [
		{
			"listen": "prerequest",
			"script": {
				"type": "text/javascript",
				"exec": [
					""
				]
			}
		},
		{
			"listen": "test",
			"script": {
				"type": "text/javascript",
				"exec": [
					""
				]
			}
		}
	]
}